dgraph/__init__.py
dgraph/dependency_graph.py
dgraph/dependency_graph_test.py
dgraph-0.0.6.dist-info/DESCRIPTION.rst
dgraph-0.0.6.dist-info/METADATA
dgraph-0.0.6.dist-info/RECORD
dgraph-0.0.6.dist-info/WHEEL
dgraph-0.0.6.dist-info/metadata.json
dgraph-0.0.6.dist-info/top_level.txt
