Metadata-Version: 2.0
Name: dgraph
Version: 0.0.6
Summary: Simple dependency graph for python functions
Home-page: https://github.com/n-s-f/dgraph
Author: UNKNOWN
Author-email: UNKNOWN
License: UNKNOWN
Platform: UNKNOWN
Requires-Dist: bunch
Requires-Dist: multiprocess
